makesense/utils.py
makesense/vcs.py
makesense/traffic.py
makesense/plot.py
makesense/run.py
makesense/report.py
makesense/sampling.py
makesense/parser.py
makesense/make.py
makesense/exceptions.py
makesense/graph.py
makesense/prompt.py
makesense/bootstrap.py
makesense/analyze.py
makesense/makesense.py
makesense/__init__.py
makesense-0.1.0.dist-info/RECORD
makesense-0.1.0.dist-info/WHEEL
makesense-0.1.0.dist-info/DESCRIPTION.rst
makesense-0.1.0.dist-info/top_level.txt
makesense-0.1.0.dist-info/metadata.json
makesense-0.1.0.dist-info/METADATA
