Metadata-Version: 2.0
Name: makesense
Version: 0.1.0
Summary: WSN utils library
Home-page: https://github.com/sieben/makesense
Author: Remy Leone
Author-email: remy.leone@telecom-paristech.fr
License: BSD
Keywords: makesense
Platform: UNKNOWN
Classifier: Development Status :: 2 - Pre-Alpha
Classifier: Intended Audience :: Developers
Classifier: License :: OSI Approved :: BSD License
Classifier: Natural Language :: English
Classifier: Programming Language :: Python :: 2
Classifier: Programming Language :: Python :: 2.6
Classifier: Programming Language :: Python :: 2.7
Classifier: Programming Language :: Python :: 3
Classifier: Programming Language :: Python :: 3.3
